ansible_vault_decrypt/__init__.py
ansible_vault_decrypt/app.py
ansible_vault_decrypt-0.0.6.dist-info/LICENSE
ansible_vault_decrypt-0.0.6.dist-info/METADATA
ansible_vault_decrypt-0.0.6.dist-info/WHEEL
ansible_vault_decrypt-0.0.6.dist-info/entry_points.txt
ansible_vault_decrypt-0.0.6.dist-info/top_level.txt
ansible_vault_decrypt-0.0.6.dist-info/RECORD
