Metadata-Version: 2.1
Name: ansible-vault-decrypt
Version: 0.0.6
Summary: Ansible Vault Decrypt app.
Home-page: https://github.com/psvmcc/ansible-vault-decrypt
Project-URL: Bug Tracker, https://github.com/psvmcc/ansible-vault-decrypt/issues
Project-URL: Changelog, https://github.com/psvmcc/ansible-vault-decrypt/releases
Classifier: Programming Language :: Python :: 3
Classifier: License :: OSI Approved :: MIT License
Classifier: Intended Audience :: Developers
Requires-Python: >=3.6
License-File: LICENSE
Requires-Dist: ansible-core
